Workbook

Sheet Dashboard
A1: DAILY STORE & ADS PERFORMANCE DASHBOARD
A2: Report Date: 2026-07-17 (Asia/Kolkata) | Store: Dhirai (dhirai.in) | Generated: 2026-07-18
A4: EXECUTIVE SUMMARY
A5: Strong day: gross sales +14.8% and orders +18.5% vs the trailing 7-day average, while Meta Ads got more efficient (CPC ~-24%, cost/purchase ~-16%, ROAS 4.06x vs a 3.62x avg). "Black DHURANDHAR" is the standout campaign (5.03x ROAS); "New Campaign- for recovery" is the lone underperformer (2.91x ROAS, lowest CTR). Watch stock-outs on the "Nritya" Anarkali line and the narrow-audience warning on ad set "Black and multiple". (Dashboard formulas pull live from the data tabs and recalculate automatically once opened in Excel/Sheets.)
A9: SHOPIFY PERFORMANCE — Yesterday vs Prior 7-Day Average
A10: Metric | B10: Yesterday | C10: 7-Day Avg | D10: Change vs Avg
A11: Gross Sales | B11: =INDEX('Shopify Daily Data'!C:C,COUNTA('Shopify Daily Data'!$A:$A)) | C11: =AVERAGE(OFFSET('Shopify Daily Data'!C1,COUNTA('Shopify Daily Data'!$A:$A)-8,0,7,1)) | D11: =(B11-C11)/C11
A12: Net Sales | B12: =INDEX('Shopify Daily Data'!F:F,COUNTA('Shopify Daily Data'!$A:$A)) | C12: =AVERAGE(OFFSET('Shopify Daily Data'!F1,COUNTA('Shopify Daily Data'!$A:$A)-8,0,7,1)) | D12: =(B12-C12)/C12
A13: Orders | B13: =INDEX('Shopify Daily Data'!B:B,COUNTA('Shopify Daily Data'!$A:$A)) | C13: =AVERAGE(OFFSET('Shopify Daily Data'!B1,COUNTA('Shopify Daily Data'!$A:$A)-8,0,7,1)) | D13: =(B13-C13)/C13
A14: Average Order Value | B14: =INDEX('Shopify Daily Data'!J:J,COUNTA('Shopify Daily Data'!$A:$A)) | C14: =AVERAGE(OFFSET('Shopify Daily Data'!J1,COUNTA('Shopify Daily Data'!$A:$A)-8,0,7,1)) | D14: =(B14-C14)/C14
A16: META ADS PERFORMANCE — Yesterday vs Prior 7-Day Average
A17: Metric | B17: Yesterday | C17: 7-Day Avg | D17: Change vs Avg
A18: Total Spend | B18: =INDEX('Meta Ads Daily Data'!B:B,COUNTA('Meta Ads Daily Data'!$A:$A)) | C18: =AVERAGE(OFFSET('Meta Ads Daily Data'!B1,COUNTA('Meta Ads Daily Data'!$A:$A)-8,0,7,1)) | D18: =(B18-C18)/C18
A19: Impressions | B19: =INDEX('Meta Ads Daily Data'!C:C,COUNTA('Meta Ads Daily Data'!$A:$A)) | C19: =AVERAGE(OFFSET('Meta Ads Daily Data'!C1,COUNTA('Meta Ads Daily Data'!$A:$A)-8,0,7,1)) | D19: =(B19-C19)/C19
A20: Clicks | B20: =INDEX('Meta Ads Daily Data'!E:E,COUNTA('Meta Ads Daily Data'!$A:$A)) | C20: =AVERAGE(OFFSET('Meta Ads Daily Data'!E1,COUNTA('Meta Ads Daily Data'!$A:$A)-8,0,7,1)) | D20: =(B20-C20)/C20
A21: CTR | B21: =INDEX('Meta Ads Daily Data'!F:F,COUNTA('Meta Ads Daily Data'!$A:$A)) | C21: =AVERAGE(OFFSET('Meta Ads Daily Data'!F1,COUNTA('Meta Ads Daily Data'!$A:$A)-8,0,7,1)) | D21: =(B21-C21)/C21
A22: CPC | B22: =INDEX('Meta Ads Daily Data'!G:G,COUNTA('Meta Ads Daily Data'!$A:$A)) | C22: =AVERAGE(OFFSET('Meta Ads Daily Data'!G1,COUNTA('Meta Ads Daily Data'!$A:$A)-8,0,7,1)) | D22: =(B22-C22)/C22
A23: Purchases | B23: =INDEX('Meta Ads Daily Data'!I:I,COUNTA('Meta Ads Daily Data'!$A:$A)) | C23: =AVERAGE(OFFSET('Meta Ads Daily Data'!I1,COUNTA('Meta Ads Daily Data'!$A:$A)-8,0,7,1)) | D23: =(B23-C23)/C23
A24: Cost per Purchase | B24: =INDEX('Meta Ads Daily Data'!J:J,COUNTA('Meta Ads Daily Data'!$A:$A)) | C24: =AVERAGE(OFFSET('Meta Ads Daily Data'!J1,COUNTA('Meta Ads Daily Data'!$A:$A)-8,0,7,1)) | D24: =(B24-C24)/C24
A25: Blended ROAS | B25: =INDEX('Meta Ads Daily Data'!K:K,COUNTA('Meta Ads Daily Data'!$A:$A)) | C25: =AVERAGE(OFFSET('Meta Ads Daily Data'!K1,COUNTA('Meta Ads Daily Data'!$A:$A)-8,0,7,1)) | D25: =(B25-C25)/C25
A28: KEY WINS
A29: ✅ Revenue up 14.8% vs 7-day avg (₹1,88,169 vs ₹1,63,941 avg) with orders up 18.5% (74 vs 62.4 avg).
A30: ✅ Meta Ads efficiency improved: CPC down ~24% (₹5.89 vs ₹7.76 avg), cost/purchase down ~16% (₹615 vs ₹730 avg), blended ROAS up to 4.06x from a 3.62x avg (+12%).
A31: ✅ "Black DHURANDHAR" campaign jumped to a 5.03x ROAS (best of all 4 campaigns) from a 7-day average of 3.08x.
A32: ✅ "Ira Rayon Co-ord Set" was the top seller (₹44,982 gross, 18 units) — consistently a top-3 performer.
A34: KEY ISSUES
A35: ⚠️ "New Campaign- for recovery" is the weakest performer: ROAS only 2.91x and lowest CTR at 1.09% (vs 3.2-3.6% on other campaigns); CPC ₹7.79 is the highest of the 4.
A36: ⚠️ Ad set "Black and multiple" flagged by Meta for a narrow audience (est. reach 22,700-26,700) while actively delivering — may be limiting scale and inflating costs.
A37: ⚠️ 25+ product variants show zero stock (notably the "Nritya" Anarkali Suit Set line across many sizes/colors and "Zariya" Stone Hoops) — risk of wasted ad clicks landing on sold-out items.
A38: ⚠️ AOV dipped 2.95% vs 7-day avg (₹2,490.78 vs ₹2,566.55) despite higher order volume — mix shifted slightly toward lower-priced items.
A40: RECOMMENDED ACTIONS FOR TODAY
A41: 1. Scale budget on "Black DHURANDHAR" (5.03x ROAS, 3.63% CTR); reallocate some spend from "New Campaign- for recovery" (2.91x ROAS) until it improves.
... A45: 5. Verify Shopify's abandoned-checkout recovery email flow is active — could not be measured this run (see Unavailable Metrics below).

Sheet Shopify Daily Data
A1: Date | B1: Orders | C1: Gross Sales | D1: Discounts | E1: Returns | F1: Net Sales | G1: Shipping | H1: Taxes | I1: Total Sales | J1: AOV
A2: 2026-07-10 | B2: 50 | C2: 121913.25 | D2: 1613.22 | E2: 0 | F2: =C2-D2-E2 | G2: 0 | H2: 533.75 | I2: =F2+G2+H2 | J2: 2406
A3: 2026-07-11 | B3: 55 | C3: 130491 | D3: 1759.27 | E3: 0 | F3: =C3-D3-E3 | G3: 0 | H3: 0 | I3: =F3+G3+H3 | J3: 2340.58
A4: 2026-07-12 | B4: 87 | C4: 269307.8 | D4: 839.65 | E4: 47285 | F4: =C4-D4-E4 | G4: 0 | H4: 381.2 | I4: =F4+G4+H4 | J4: 3085.84
A5: 2026-07-13 | B5: 55 | C5: 142333.07 | D5: 3105.69 | E5: 0 | F5: =C5-D5-E5 | G5: 0 | H5: 304.93 | I5: =F5+G5+H5 | J5: 2531.41
A6: 2026-07-14 | B6: 57 | C6: 144836 | D6: 314.85 | E6: 1999 | F6: =C6-D6-E6 | G6: 0 | H6: 0 | I6: =F6+G6+H6 | J6: 2535.46
A7: 2026-07-15 | B7: 64 | C7: 166129 | D7: 1092.05 | E7: 0 | F7: =C7-D7-E7 | G7: 0 | H7: 0 | I7: =F7+G7+H7 | J7: 2578.7
A8: 2026-07-16 | B8: 69 | C8: 172575 | D8: 914.6 | E8: 2199 | F8: =C8-D8-E8 | G8: 0 | H8: 0 | I8: =F8+G8+H8 | J8: 2487.83
A9: 2026-07-17 | B9: 74 | C9: 188169 | D9: 3851.24 | E9: 0 | F9: =C9-D9-E9 | G9: 0 | H9: 0 | I9: =F9+G9+H9 | J9: 2490.78
A11: Note: Net Sales = Gross Sales − Discounts − Returns. Total Sales = Net Sales + Shipping + Taxes. AOV as reported by Shopify Analytics. Source: Shopify Admin/ShopifyQL, store 36dhns-ed.myshopify.com (Dhirai), timezone Asia/Kolkata.

Sheet Meta Ads Daily Data
A1: Date | B1: Spend | C1: Impressions | D1: Reach | E1: Clicks | F1: CTR | G1: CPC | H1: CPM | I1: Purchases | J1: Cost per Purchase | K1: ROAS
A2: 2026-07-10 | B2: 41607.98 | C2: 247234 | D2: 207925 | E2: 5570 | F2: =E2/C2 | G2: =B2/E2 | H2: =B2/C2*1000 | I2: 47 | J2: =B2/I2 | K2: 2.7
A3: 2026-07-11 | B3: 35653.1 | C3: 216060 | D3: 180186 | E3: 4684 | F3: =E3/C3 | G3: =B3/E3 | H3: =B3/C3*1000 | I3: 53 | J3: =B3/I3 | K3: 3.49
A4: 2026-07-12 | B4: 47584.42 | C4: 259228 | D4: 214990 | E4: 5765 | F4: =E4/C4 | G4: =B4/E4 | H4: =B4/C4*1000 | I4: 84 | J4: =B4/I4 | K4: 5.45
A5: 2026-07-13 | B5: 45884.99 | C5: 236170 | D5: 184417 | E5: 5178 | F5: =E5/C5 | G5: =B5/E5 | H5: =B5/C5*1000 | I5: 54 | J5: =B5/I5 | K5: 3
A6: 2026-07-14 | B6: 44951.34 | C6: 232320 | D6: 189826 | E6: 5440 | F6: =E6/C6 | G6: =B6/E6 | H6: =B6/C6*1000 | I6: 57 | J6: =B6/I6 | K6: 3.17
A7: 2026-07-15 | B7: 43931.17 | C7: 254112 | D7: 199911 | E7: 6195 | F7: =E7/C7 | G7: =B7/E7 | H7: =B7/C7*1000 | I7: 61 | J7: =B7/I7 | K7: 3.62
A8: 2026-07-16 | B8: 43468.39 | C8: 279467 | D8: 216156 | E8: 6412 | F8: =E8/C8 | G8: =B8/E8 | H8: =B8/C8*1000 | I8: 69 | J8: =B8/I8 | K8: 3.94
A9: 2026-07-17 | B9: 44910.35 | C9: 340946 | D9: 263644 | E9: 7625 | F9: =E9/C9 | G9: =B9/E9 | H9: =B9/C9*1000 | I9: 73 | J9: =B9/I9 | K9: 4.06
A11: Note: CTR = Clicks/Impressions, CPC = Spend/Clicks, CPM = Spend/Impressions*1000, Cost per Purchase = Spend/Purchases (all formulas). Purchases = Meta 'omni_purchase' action. ROAS is Meta-reported purchase ROAS (value not independently derivable from fields available). Source: Meta Ads Manager, ad account 979830497515712 (Dhirai).

Sheet Product Performance
A1: PRODUCT PERFORMANCE — Snapshot for 2026-07-17 (updated each run)
A2: Product | B2: Gross Sales | C2: Net Sales | D2: Orders | E2: Units Sold | F2: Avg Item Value
A3: Ira Rayon Co-ord Set for Women | Relaxed Fit Shirt Top with Draped Pants | B3: 44982 | C3: 44732.1 | D3: 18 | E3: 18 | F3: =B3/D3
A4: "The Essential" - White Cotton Shirt & Pant Co-ord Set | B4: 28386 | C4: 28386 | D4: 13 | E4: 14 | F4: =B4/D4
A5: The Dhurandhar Black Short Kurta Set | A Dhirai Essential | B5: 15743 | C5: 15405.65 | D5: 5 | E5: 7 | F5: =B5/D5
A6: Embroidered Rayon Kurti with Farshi Salwar Set — Elegant Ethnic Co-Ord for Women | B6: 11196 | C6: 11056.05 | D6: 4 | E6: 4 | F6: =B6/D6
A7: Zehra Co-ord set| DHIRAI | B7: 9996 | C7: 9996 | D7: 4 | E7: 4 | F7: =B7/D7
A8: Elegant Pakistani-Style Mauve Kurta Set | B8: 8096 | C8: 8096 | D8: 4 | E8: 4 | F8: =B8/D8
A9: "Inayat" — Power Pastel Cotton Shirt & Trouser Co-ord Set | B9: 7996 | C9: 7996 | D9: 4 | E9: 4 | F9: =B9/D9
A10: Sage Aura cotton Kurta Set | DHIRAI | B10: 4198 | C10: 4198 | D10: 2 | E10: 2 | F10: =B10/D10
A11: "Arushi" - Red Georgette Full Flare Anarkali Suit Set with Gold Gota | B11: 3999 | C11: 3999 | D11: 1 | E11: 1 | F11: =B11/D11
A12: Premium Cotton Linen Blend Shirt & Pant Coord Set | B12: 3998 | C12: 2734.63 | D12: 1 | E12: 2 | F12: =B12/D12
A13: Everyday Elegance Cotton Kurta Pant Set | B13: 3998 | C13: 3998 | D13: 2 | E13: 2 | F13: =B13/D13
A14: "Riva" — Premium Flowy Rayon Co-ord Set | B14: 3998 | C14: 3998 | D14: 2 | E14: 2 | F14: =B14/D14
... A17: Eclipse Grace Premium Crepe Salwar Suit set | DHIRAI | B17: 2999 | C17: 2999 | D17: 1 | E17: 1 | F17: =B17/D17
A19: Snapshot reflects the most recently reviewed business day only (overwritten each run); full daily trend lives in 'Shopify Daily Data'. Source: Shopify ShopifyQL sales + inventory reports.

Sheet Campaign Performance
A1: CAMPAIGN PERFORMANCE — Snapshot for 2026-07-17 (updated each run)
A2: Campaign | B2: Status | C2: Spend | D2: Impressions | E2: Clicks | F2: CTR | G2: CPC | H2: Purchases | I2: Cost per Purchase | J2: ROAS
A3: Black DHURANDHAR | B3: Active | C3: 8083.58 | D3: 58243 | E3: 2113 | F3: =E3/D3 | G3: =C3/E3 | H3: 15 | I3: =C3/H3 | J3: 5.03
A4: Dhirai Scale -ASC | B4: Active | C4: 13935.16 | D4: 84560 | E4: 2703 | F4: =E4/D4 | G4: =C4/E4 | H4: 27 | I4: =C4/H4 | J4: 4.5
A5: Retargeting- new | B5: Active | C5: 8242.68 | D5: 26215 | E5: 928 | F5: =E5/D5 | G5: =C5/E5 | H5: 14 | I5: =C5/H5 | J5: 4.44
A6: New Campaign- for recovery | B6: Active | C6: 14648.93 | D6: 171928 | E6: 1881 | F6: =E6/D6 | G6: =C6/E6 | H6: 17 | I6: =C6/H6 | J6: 2.91
A8: All 4 active campaigns shown (ad account matched to Shopify store 'Dhirai' by name, ID 979830497515712). Snapshot reflects the most recently reviewed day only; full daily trend lives in 'Meta Ads Daily Data'. Ad-set/ad level breakdown was not queryable this run — see Recommendations & Notes.

Sheet Recommendations & Notes
A1: RECOMMENDATIONS & NOTES
A3: ── 2026-07-17 ──
A4: KEY WINS
A5: ✅ | B5: Revenue up 14.8% vs 7-day avg (₹1,88,169 vs ₹1,63,941 avg) with orders up 18.5% (74 vs 62.4 avg).
A6: ✅ | B6: Meta Ads efficiency improved: CPC down ~24% (₹5.89 vs ₹7.76 avg), cost/purchase down ~16% (₹615 vs ₹730 avg), blended ROAS up to 4.06x from a 3.62x avg (+12%).
A7: ✅ | B7: "Black DHURANDHAR" campaign jumped to a 5.03x ROAS (best of all 4 campaigns) from a 7-day average of 3.08x.
A8: ✅ | B8: "Ira Rayon Co-ord Set" was the top seller (₹44,982 gross, 18 units) — consistently a top-3 performer.
A10: KEY ISSUES
A11: ⚠️ | B11: "New Campaign- for recovery" is the weakest performer: ROAS only 2.91x and lowest CTR at 1.09% (vs 3.2-3.6% on other campaigns); CPC ₹7.79 is the highest of the 4.
A12: ⚠️ | B12: Ad set "Black and multiple" flagged by Meta for a narrow audience (est. reach 22,700-26,700) while actively delivering — may be limiting scale and inflating costs.
A13: ⚠️ | B13: 25+ product variants show zero stock (notably the "Nritya" Anarkali Suit Set line across many sizes/colors and "Zariya" Stone Hoops) — risk of wasted ad clicks landing on sold-out items.
A14: ⚠️ | B14: AOV dipped 2.95% vs 7-day avg (₹2,490.78 vs ₹2,566.55) despite higher order volume — mix shifted slightly toward lower-priced items.
A16: RECOMMENDED ACTIONS FOR TODAY
A17: 1 | B17: Scale budget on "Black DHURANDHAR" (5.03x ROAS, 3.63% CTR); reallocate some spend from "New Campaign- for recovery" (2.91x ROAS) until it improves.
A18: 2 | B18: Enable Advantage+ Audience on "Retargeting- new" and "Black and multiple" ad sets — Meta estimates ~11% lower cost per purchase.
A19: 3 | B19: Restock or temporarily unpublish the out-of-stock "Nritya" Anarkali Suit Set variants and "Zariya" Stone Hoops to stop paid traffic from hitting sold-out pages.
A20: 4 | B20: Consolidate the fragmented ad sets inside "New Campaign- for recovery" per Meta's fragmentation warning (est. +6 pt opportunity score, more sales at the same spend).
A21: 5 | B21: Verify Shopify's abandoned-checkout recovery email flow is active — could not be measured this run (see Unavailable Metrics below).
A23: UNAVAILABLE METRICS / DATA NOTES
A24: ℹ️ | B24: Google Sheets was not connected this session, so this dashboard was delivered as an Excel (.xlsx) workbook attached to the summary email instead of a Google Sheet link.
A25: ℹ️ | B25: Failed payments: not exposed by the Shopify tools available this run.
A26: ℹ️ | B26: Abandoned checkouts: not exposed by the Shopify analytics/order tools available this run.
A27: ℹ️ | B27: Cancellations: no distinct cancelled-order count was queryable this run; the 74 orders on 2026-07-17 showed only Pending/Paid financial statuses in the sample reviewed.
A28: ℹ️ | B28: Meta ad-set and ad-level cost/CPA breakdown: campaign-level data, an audience-size anomaly signal, and account Opportunity Score were captured; extended ad-set metrics (cost_per_omni_purchase, conversions) returned field-validation errors and were omitted.
A29: ℹ️ | B29: Meta ad account: 'Dhirai' (ID 979830497515712) was matched to the Shopify store 'Dhirai' (36dhns-ed.myshopify.com) by name out of 45 accessible ad accounts — please confirm this is the correct account if it should differ.
A30: ℹ️ | B30: Dashboard formulas (INDEX/OFFSET/AVERAGE) use only standard, widely-supported Excel functions and were manually verified against the source data; live recalculation could not be run this session because the sandbox's LibreOffice could not load any file (even its own sample documents), so cells may show blank until you open the file in Excel or Google Sheets, which will calculate them automatically.
