Workbook

Sheet Dashboard
A1: DAILY STORE & ADS PERFORMANCE DASHBOARD
A2: Reporting date (Asia/Kolkata): 2026-07-18 | Store: 36dhns-ed.myshopify.com | Currency: INR
A4: EXECUTIVE SUMMARY
A5: Both Shopify revenue and Meta Ads purchases fell sharply yesterday vs. the trailing 7-day average.
A6: Ad efficiency (CPC, CPM) improved, but ROAS and CPA moved the wrong way as purchase volume dropped.
A7: One ad set is running below breakeven and one is flagged for a narrow audience — see Campaign Performance tab.
A9: SHOPIFY PERFORMANCE
A10: Metric | B10: Yesterday | C10: 7-Day Avg | D10: Change vs Avg
A11: Gross Sales | B11: =INDEX('Shopify Daily Data'!B:B,COUNTA('Shopify Daily Data'!A:A)) | C11: =IFERROR(AVERAGE(OFFSET('Shopify Daily Data'!B1,COUNTA('Shopify Daily Data'!A:A)-8,0,7,1)),"n/a") | D11: =IFERROR((B11-C11)/C11,"n/a")
A12: Net Sales | B12: =INDEX('Shopify Daily Data'!C:C,COUNTA('Shopify Daily Data'!A:A)) | C12: =IFERROR(AVERAGE(OFFSET('Shopify Daily Data'!C1,COUNTA('Shopify Daily Data'!A:A)-8,0,7,1)),"n/a") | D12: =IFERROR((B12-C12)/C12,"n/a")
A13: Orders | B13: =INDEX('Shopify Daily Data'!D:D,COUNTA('Shopify Daily Data'!A:A)) | C13: =IFERROR(AVERAGE(OFFSET('Shopify Daily Data'!D1,COUNTA('Shopify Daily Data'!A:A)-8,0,7,1)),"n/a") | D13: =IFERROR((B13-C13)/C13,"n/a")
A14: Avg Order Value | B14: =INDEX('Shopify Daily Data'!E:E,COUNTA('Shopify Daily Data'!A:A)) | C14: =IFERROR(AVERAGE(OFFSET('Shopify Daily Data'!E1,COUNTA('Shopify Daily Data'!A:A)-8,0,7,1)),"n/a") | D14: =IFERROR((B14-C14)/C14,"n/a")
A15: Returns | B15: =INDEX('Shopify Daily Data'!H:H,COUNTA('Shopify Daily Data'!A:A)) | C15: =IFERROR(AVERAGE(OFFSET('Shopify Daily Data'!H1,COUNTA('Shopify Daily Data'!A:A)-8,0,7,1)),"n/a") | D15: =IFERROR((B15-C15)/C15,"n/a")
A17: META ADS PERFORMANCE
A18: Metric | B18: Yesterday | C18: 7-Day Avg | D18: Change vs Avg
A19: Spend | B19: =INDEX('Meta Ads Daily Data'!B:B,COUNTA('Meta Ads Daily Data'!A:A)) | C19: =IFERROR(AVERAGE(OFFSET('Meta Ads Daily Data'!B1,COUNTA('Meta Ads Daily Data'!A:A)-8,0,7,1)),"n/a") | D19: =IFERROR((B19-C19)/C19,"n/a")
A20: Purchases | B20: =INDEX('Meta Ads Daily Data'!I:I,COUNTA('Meta Ads Daily Data'!A:A)) | C20: =IFERROR(AVERAGE(OFFSET('Meta Ads Daily Data'!I1,COUNTA('Meta Ads Daily Data'!A:A)-8,0,7,1)),"n/a") | D20: =IFERROR((B20-C20)/C20,"n/a")
A21: CPA | B21: =INDEX('Meta Ads Daily Data'!J:J,COUNTA('Meta Ads Daily Data'!A:A)) | C21: =IFERROR(AVERAGE(OFFSET('Meta Ads Daily Data'!J1,COUNTA('Meta Ads Daily Data'!A:A)-8,0,7,1)),"n/a") | D21: =IFERROR((B21-C21)/C21,"n/a")
A22: ROAS | B22: =INDEX('Meta Ads Daily Data'!K:K,COUNTA('Meta Ads Daily Data'!A:A)) | C22: =IFERROR(AVERAGE(OFFSET('Meta Ads Daily Data'!K1,COUNTA('Meta Ads Daily Data'!A:A)-8,0,7,1)),"n/a") | D22: =IFERROR((B22-C22)/C22,"n/a")
A23: CTR | B23: =INDEX('Meta Ads Daily Data'!F:F,COUNTA('Meta Ads Daily Data'!A:A)) | C23: =IFERROR(AVERAGE(OFFSET('Meta Ads Daily Data'!F1,COUNTA('Meta Ads Daily Data'!A:A)-8,0,7,1)),"n/a") | D23: =IFERROR((B23-C23)/C23,"n/a")
A24: CPC | B24: =INDEX('Meta Ads Daily Data'!G:G,COUNTA('Meta Ads Daily Data'!A:A)) | C24: =IFERROR(AVERAGE(OFFSET('Meta Ads Daily Data'!G1,COUNTA('Meta Ads Daily Data'!A:A)-8,0,7,1)),"n/a") | D24: =IFERROR((B24-C24)/C24,"n/a")
A26: KEY WINS
A27: • | B27: Campaign 'Retargeting- new' delivered ROAS 4.42x yesterday (its ad set 'Best performing ads' hit 5.51x) — a strong scale candidate.
A28: • | B28: Ad efficiency improved: CPC down 17.2% and CPM down 12.2% vs the 7-day average.
A29: • | B29: 'Ira Rayon Co-ord Set' remains the top seller, ₹29,988 yesterday and ₹307,377 over the trailing 7 days.
A31: KEY ISSUES
A32: • | B32: Gross sales fell 39.3% and orders fell 37.7% vs the 7-day average — the steepest single-day drop of the week.
A33: • | B33: Meta purchases fell 41.0% and ROAS fell from 3.84x to 2.82x (-26.6%) while CPA rose 33.9% to ₹909.
A34: • | B34: Ad set 'White Dhurandhar' is running at ROAS 0.95x — below breakeven.
A35: • | B35: Ad set 'Black and multiple' was flagged by Meta for a narrow audience (~23K-27K reach).
A36: • | B36: Shopify's checkout-completion tracking shows 0-1 sessions/day all week despite 41-87 real orders/day — looks like a tracking/pixel gap, not a real conversion problem.
A38: RECOMMENDED ACTIONS FOR TODAY
A39: • | B39: 1. Scale budget 20-30% on the 'Retargeting- new' campaign / 'Best performing ads' ad set given its 5.51x ROAS.
A40: • | B40: 2. Pause or refresh creative on the 'White Dhurandhar' ad set (ROAS 0.95x, below breakeven).
A41: • | B41: 3. Expand the audience (or test Advantage+ audience) on 'Black and multiple' to fix the narrow-audience warning.
A42: • | B42: 4. Investigate yesterday's steep order/revenue drop — check payment gateway status, site uptime, and ad delivery pacing together.
A43: • | B43: 5. Review Shopify's checkout/pixel tracking configuration — completed-checkout sessions do not reconcile with real order volume.

Sheet Shopify Daily Data
A1: Date | B1: Gross Sales | C1: Net Sales | D1: Orders | E1: AOV | F1: Total Sales | G1: Discounts | H1: Returns | I1: Shipping | J1: Taxes | K1: Sessions | L1: Cart Adds | M1: Reached Checkout | N1: Completed Checkout | O1: Conversion Rate
A2: 2026-07-11 | B2: 130491 | C2: 128731.73 | D2: 55 | E2: 2340.576 | F2: 128731.73 | G2: -1759.27 | H2: 0 | I2: 0 | J2: 0 | K2: 3221 | M2: 2 | N2: 0
A3: 2026-07-12 | B3: 269307.8 | C3: 221183.15 | D3: 87 | E3: 3085.84 | F3: 221564.35 | G3: -839.65 | H3: -47285 | I3: 0 | J3: 381.2 | K3: 3940 | M3: 2 | N3: 1
A4: 2026-07-13 | B4: 142333.07 | C4: 139227.38 | D4: 55 | E4: 2531.406 | F4: 139532.31 | G4: -3105.69 | H4: 0 | I4: 0 | J4: 304.93 | K4: 3532 | M4: 4 | N4: 1
A5: 2026-07-14 | B5: 144836 | C5: 142522.15 | D5: 57 | E5: 2535.458 | F5: 142522.15 | G5: -314.85 | H5: -1999 | I5: 0 | J5: 0 | K5: 3564 | M5: 2 | N5: 0
A6: 2026-07-15 | B6: 166129 | C6: 165036.95 | D6: 64 | E6: 2578.702 | F6: 165036.95 | G6: -1092.05 | H6: 0 | I6: 0 | J6: 0 | K6: 3815 | M6: 1 | N6: 0
A7: 2026-07-16 | B7: 172575 | C7: 169461.4 | D7: 69 | E7: 2487.831 | F7: 169461.4 | G7: -914.6 | H7: -2199 | I7: 0 | J7: 0 | K7: 4049 | M7: 2 | N7: 0
A8: 2026-07-17 | B8: 188169 | C8: 184317.76 | D8: 74 | E8: 2490.78 | F8: 184317.76 | G8: -3851.24 | H8: 0 | I8: 0 | J8: 0 | K8: 4890 | M8: 2 | N8: 0
A9: 2026-07-18 | B9: 105255 | C9: 105155.05 | D9: 41 | E9: 2564.757 | F9: 105155.05 | G9: -99.95 | H9: 0 | I9: 0 | J9: 0 | K9: 3695 | L9: 223 | M9: 1 | N9: 0 | O9: 0

Sheet Meta Ads Daily Data
A1: Date | B1: Spend | C1: Impressions | D1: Reach | E1: Clicks | F1: CTR | G1: CPC | H1: CPM | I1: Purchases | J1: CPA | K1: ROAS
A2: 2026-07-11 | B2: 35653.1 | C2: 216060 | D2: 180186 | E2: 4684 | F2: 0.0217 | G2: 7.61 | H2: 165.01 | I2: 53 | J2: 672.7 | K2: 3.49
A3: 2026-07-12 | B3: 47584.42 | C3: 259228 | D3: 214990 | E3: 5765 | F3: 0.0222 | G3: 8.25 | H3: 183.56 | I3: 84 | J3: 566.48 | K3: 5.45
A4: 2026-07-13 | B4: 45884.99 | C4: 236170 | D4: 184417 | E4: 5178 | F4: 0.0219 | G4: 8.86 | H4: 194.29 | I4: 54 | J4: 849.72 | K4: 3
A5: 2026-07-14 | B5: 44951.34 | C5: 232320 | D5: 189826 | E5: 5440 | F5: 0.0234 | G5: 8.26 | H5: 193.49 | I5: 57 | J5: 788.62 | K5: 3.17
A6: 2026-07-15 | B6: 43931.17 | C6: 254112 | D6: 199911 | E6: 6195 | F6: 0.0244 | G6: 7.09 | H6: 172.88 | I6: 61 | J6: 720.18 | K6: 3.62
A7: 2026-07-16 | B7: 43468.39 | C7: 279467 | D7: 216156 | E7: 6412 | F7: 0.0229 | G7: 6.78 | H7: 155.54 | I7: 69 | J7: 629.98 | K7: 3.94
A8: 2026-07-17 | B8: 44911.73 | C8: 340954 | D8: 263644 | E8: 7625 | F8: 0.0224 | G8: 5.89 | H8: 131.72 | I8: 73 | J8: 615.23 | K8: 4.06
A9: 2026-07-18 | B9: 34547.04 | C9: 233531 | D9: 185932 | E9: 5627 | F9: 0.0241 | G9: 6.14 | H9: 147.93 | I9: 38 | J9: 909.13 | K9: 2.82

Sheet Product Performance
A1: PRODUCT PERFORMANCE — Yesterday (2026-07-18) vs Trailing 7 Days
A3: Product | B3: Gross Sales | C3: Net Sales | D3: Orders | E3: Total Sales
A4: Ira Rayon Co-ord Set for Women | Relaxed Fit Shirt Top with Draped Pants | B4: 29988 | C4: 29988 | D4: 12 | E4: 29988
A5: "The Essential" - White Cotton Shirt & Pant Co-ord Set | B5: 18191 | C5: 18091.05 | D5: 9 | E5: 18091.05
A6: Everyday Elegance Cotton Kurta Pant Set | B6: 7996 | C6: 7996 | D6: 3 | E6: 7996
A7: Noor Sand Kurta Set | B7: 6998 | C7: 6998 | D7: 2 | E7: 6998
A8: "Inayat" - Power Pastel Cotton Shirt & Trouser Co-ord Set | B8: 5997 | C8: 5997 | D8: 3 | E8: 5997
A9: Elegant Pakistani-Style Mauve Kurta Set | B9: 3998 | C9: 3998 | D9: 2 | E9: 3998
A10: Vidhya Georgette Suit Set | B10: 3499 | C10: 3499 | D10: 1 | E10: 3499
A11: "Aura" - Cream Lightweight Breathable Lace-Detail Suit Set | B11: 3299 | C11: 3299 | D11: 1 | E11: 3299
A12: "Gaja" - Handblock Print Cotton Co-ord Set | B12: 2799 | C12: 2799 | D12: 1 | E12: 2799
A13: Embroidered Rayon Kurti with Farshi Salwar Set - Elegant Ethnic Co-Ord for Women | B13: 2799 | C13: 2799 | D13: 1 | E13: 2799
A15: 7-DAY TOP PRODUCTS (2026-07-11 to 2026-07-17)
A16: Product | B16: Gross Sales | C16: Net Sales | D16: Orders | E16: Total Sales
A17: Ira Rayon Co-ord Set for Women | Relaxed Fit Shirt Top with Draped Pants | B17: 307377 | C17: 305212.87 | D17: 114 | E17: 305212.87
A18: "The Essential" - White Cotton Shirt & Pant Co-ord Set | B18: 233585 | C18: 230981.2 | D18: 110 | E18: 230981.2
A19: The Dhurandhar Black Short Kurta Set | A Dhirai Essential | B19: 56825 | C19: 54565.93 | D19: 21 | E19: 54565.93
A20: Embroidered Rayon Kurti with Farshi Salwar Set - Elegant Ethnic Co-Ord for Women | B20: 41985 | C20: 41565.15 | D20: 15 | E20: 41565.15
A21: "Inayat" - Power Pastel Cotton Shirt & Trouser Co-ord Set | B21: 41979 | C21: 41779.1 | D21: 20 | E21: 41779.1
A22: Elegant Pakistani-Style Mauve Kurta Set | B22: 39975.07 | C22: 37976.07 | D22: 20 | E22: 38281
A23: "Riva" - Premium Flowy Rayon Co-ord Set | B23: 32384 | C23: 32384 | D23: 15 | E23: 32384
A24: Eclipse Grace Premium Crepe Salwar Suit set | DHIRAI | B24: 26991 | C24: 26991 | D24: 8 | E24: 26991
A25: Everyday Elegance Cotton Kurta Pant Set | B25: 25987 | C25: 23356.32 | D25: 13 | E25: 23356.32
A26: "Aina" - Ivory Breathable Cotton Mirror Work Coord Set | B26: 19794 | C26: 0 | D26: 3 | E26: 0

Sheet Campaign Performance
A1: META ADS — CAMPAIGN & AD SET PERFORMANCE (2026-07-18)
A3: Campaign | B3: Status | C3: Spend | D3: Impressions | E3: Reach | F3: Clicks | G3: CTR | H3: CPC | I3: CPM | J3: Purchases | K3: CPA | L3: ROAS
A4: Dhirai Scale -ASC | B4: ACTIVE | C4: 11206.13 | D4: 63719 | E4: 55244 | F4: 2065 | G4: 0.0324 | H4: 5.43 | I4: 175.87 | J4: 13 | K4: 862.01 | L4: 2.66
A5: New Campaign- for recovery | B5: ACTIVE | C5: 10411.94 | D5: 108513 | E5: 94459 | F5: 1246 | G5: 0.0115 | H5: 8.36 | I5: 95.95 | J5: 11 | K5: 946.54 | L5: 2.59
A6: Black DHURANDHAR | B6: ACTIVE | C6: 6623.22 | D6: 40540 | E6: 35669 | F6: 1513 | G6: 0.0373 | H6: 4.38 | I6: 163.37 | J6: 6 | K6: 1103.87 | L6: 1.9
A7: Retargeting- new | B7: ACTIVE | C7: 6305.75 | D7: 20759 | E7: 13594 | F7: 803 | G7: 0.0387 | H7: 7.85 | I7: 303.76 | J7: 8 | K7: 788.22 | L7: 4.42
A9: AD SET LEVEL PERFORMANCE
A10: Ad Set | B10: Campaign | C10: Spend | D10: Impressions | E10: Reach | F10: Clicks | G10: CTR | H10: CPC | I10: CPM | J10: Purchases | K10: CPA | L10: ROAS
A11: New Sales Ad Set | B11: Dhirai Scale -ASC | C11: 10889.29 | D11: 62604 | E11: 54421 | F11: 2018 | G11: 0.0322 | H11: 5.4 | I11: 173.94 | J11: 13 | K11: 837.64 | L11: 2.74
A12: Rayon | B12: New Campaign- for recovery | C12: 8257.58 | D12: 96197 | E12: 83913 | F12: 1065 | G12: 0.0111 | H12: 7.75 | I12: 85.84 | J12: 10 | K12: 825.76 | L12: 3.03
A13: Broad | B13: Black DHURANDHAR | C13: 6623.22 | D13: 40540 | E13: 35669 | F13: 1513 | G13: 0.0373 | H13: 4.38 | I13: 163.37 | J13: 6 | K13: 1103.87 | L13: 1.9
A14: Best performing ads | B14: Retargeting- new | C14: 4697.84 | D14: 15470 | E14: 10816 | F14: 541 | G14: 0.035 | H14: 8.68 | I14: 303.67 | J14: 7 | K14: 671.12 | L14: 5.51
A15: White Dhurandhar | B15: New Campaign- for recovery | C15: 2110.6 | D15: 12135 | E15: 11079 | F15: 178 | G15: 0.0147 | H15: 11.86 | I15: 173.93 | J15: 1 | K15: 2110.6 | L15: 0.95
A16: Black and multiple | B16: Retargeting- new | C16: 1607.91 | D16: 5289 | E16: 3985 | F16: 262 | G16: 0.0495 | H16: 6.14 | I16: 304.01 | J16: 1 | K16: 1607.91 | L16: 1.24
A17: Karigari | B17: Dhirai Scale -ASC | C17: 316.84 | D17: 1115 | E17: 951 | F17: 47 | G17: 0.0422 | H17: 6.74 | I17: 284.16
A18: Karigar | B18: New Campaign- for recovery | C18: 30.27 | D18: 139 | E18: 132 | F18: 2 | G18: 0.0144 | H18: 15.14 | I18: 217.77
A19: Black Dhurandhar | B19: New Campaign- for recovery | C19: 13.49 | D19: 42 | E19: 39 | F19: 1 | G19: 0.0238 | H19: 13.49 | I19: 321.19

Sheet Recommendations & Notes
A1: RECOMMENDATIONS & NOTES — 2026-07-18
A3: KEY WINS
B4: Campaign 'Retargeting- new' delivered ROAS 4.42x yesterday (its ad set 'Best performing ads' hit 5.51x) — a strong scale candidate.
B5: Ad efficiency improved: CPC down 17.2% and CPM down 12.2% vs the 7-day average.
B6: 'Ira Rayon Co-ord Set' remains the top seller, ₹29,988 yesterday and ₹307,377 over the trailing 7 days.
A8: KEY ISSUES
B9: Gross sales fell 39.3% and orders fell 37.7% vs the 7-day average — the steepest single-day drop of the week.
B10: Meta purchases fell 41.0% and ROAS fell from 3.84x to 2.82x (-26.6%) while CPA rose 33.9% to ₹909.
B11: Ad set 'White Dhurandhar' is running at ROAS 0.95x — below breakeven.
B12: Ad set 'Black and multiple' was flagged by Meta for a narrow audience (~23K-27K reach).
B13: Shopify's checkout-completion tracking shows 0-1 sessions/day all week despite 41-87 real orders/day — looks like a tracking/pixel gap, not a real conversion problem.
A15: RECOMMENDED ACTIONS FOR TODAY
B16: 1. Scale budget 20-30% on the 'Retargeting- new' campaign / 'Best performing ads' ad set given its 5.51x ROAS.
B17: 2. Pause or refresh creative on the 'White Dhurandhar' ad set (ROAS 0.95x, below breakeven).
B18: 3. Expand the audience (or test Advantage+ audience) on 'Black and multiple' to fix the narrow-audience warning.
B19: 4. Investigate yesterday's steep order/revenue drop — check payment gateway status, site uptime, and ad delivery pacing together.
B20: 5. Review Shopify's checkout/pixel tracking configuration — completed-checkout sessions do not reconcile with real order volume.
A22: ANOMALY SIGNALS (Meta Ads)
B23: Ad set 'Black and multiple' (Retargeting- new): actively delivering to a narrow audience (est. 23,100-27,200 reach). Recommendation: expand audience or A/B test Advantage+ audience.
A25: TRACKING NOTE
B26: Shopify's sessions_that_completed_checkout metric reported 0-1 per day all week despite 41-87 real orders/day per the sales table - this looks like a checkout/pixel attribution gap in Shopify analytics, not an actual conversion problem. Recommend having someone check the Shopify Analytics/pixel configuration.
A28: UNAVAILABLE METRICS / DATA NOTES
B29: Failed payments: not exposed by the Shopify ShopifyQL analytics endpoints available in this session.
B30: Abandoned checkouts (count/value): not exposed by the Shopify ShopifyQL analytics endpoints available in this session; sessions_that_reached_checkout is used as a partial proxy.
B31: Order-level cancellation and refund reasons: only the aggregate 'returns' total is available via ShopifyQL; per-order detail requires the Shopify Admin UI.
B32: Financial status breakdown (pending/paid/refunded): ShopifyQL rejected 'financial_status' / 'order_financial_status' as unknown columns - not queryable via the analytics API in this session.
B33: Google Sheets: no Google Sheets connector was available in this session, so this dashboard was delivered as an Excel workbook instead.
B34: Direct email send / attaching this file to a Gmail draft: not supported by the Gmail tools available in this session (draft-only, no attachments) - the workbook was committed to the claude-routines repo and linked instead.
