Workbook

Sheet Dashboard
A1: Daily Store & Ads Performance Dashboard
A2: Report Date: 2026-07-01 (Asia/Kolkata) | Generated: 2026-07-02 | Store: Dhirai (dhirai.in) | Ad Account: Dhirai (Meta)
A4: 1. EXECUTIVE SUMMARY
A5: Yesterday was a strong day: Shopify orders and revenue rose well above the 7-day average, and Meta Ads
A6: delivered more purchases at a better ROAS than its recent trend. No refunds, cancellations, or payment
A7: failures were recorded yesterday. Two watch items: session/conversion-rate tracking data has not yet
A8: landed for yesterday (pipeline lag), and 2 SKUs show zero inventory.
A10: 2. SHOPIFY PERFORMANCE — Yesterday vs Previous 7-Day Average
A11: Metric | B11: Yesterday | C11: Previous 7-Day Avg | D11: Change %
A12: Orders | B12: ='Shopify Daily Data'!B9 | C12: =AVERAGE('Shopify Daily Data'!B2:B8) | D12: =IFERROR((B12-C12)/C12,0)
A13: Gross Sales | B13: ='Shopify Daily Data'!C9 | C13: =AVERAGE('Shopify Daily Data'!C2:C8) | D13: =IFERROR((B13-C13)/C13,0)
A14: Net Sales | B14: ='Shopify Daily Data'!F9 | C14: =AVERAGE('Shopify Daily Data'!F2:F8) | D14: =IFERROR((B14-C14)/C14,0)
A15: Refunds/Returns | B15: ='Shopify Daily Data'!E9 | C15: =AVERAGE('Shopify Daily Data'!E2:E8) | D15: =IFERROR((B15-C15)/C15,0)
A16: Avg Order Value | B16: ='Shopify Daily Data'!J9 | C16: =AVERAGE('Shopify Daily Data'!J2:J8) | D16: =IFERROR((B16-C16)/C16,0)
A18: 3. META ADS PERFORMANCE — Yesterday vs Previous 7-Day Average
A19: Metric | B19: Yesterday | C19: Previous 7-Day Avg | D19: Change %
A20: Amount Spent | B20: ='Meta Ads Daily Data'!B9 | C20: =AVERAGE('Meta Ads Daily Data'!B2:B8) | D20: =IFERROR((B20-C20)/C20,0)
A21: Impressions | B21: ='Meta Ads Daily Data'!C9 | C21: =AVERAGE('Meta Ads Daily Data'!C2:C8) | D21: =IFERROR((B21-C21)/C21,0)
A22: Reach | B22: ='Meta Ads Daily Data'!D9 | C22: =AVERAGE('Meta Ads Daily Data'!D2:D8) | D22: =IFERROR((B22-C22)/C22,0)
A23: Clicks | B23: ='Meta Ads Daily Data'!E9 | C23: =AVERAGE('Meta Ads Daily Data'!E2:E8) | D23: =IFERROR((B23-C23)/C23,0)
A24: CTR | B24: ='Meta Ads Daily Data'!F9 | C24: =AVERAGE('Meta Ads Daily Data'!F2:F8) | D24: =IFERROR((B24-C24)/C24,0)
A25: CPC | B25: ='Meta Ads Daily Data'!G9 | C25: =AVERAGE('Meta Ads Daily Data'!G2:G8) | D25: =IFERROR((B25-C25)/C25,0)
A26: Purchases | B26: ='Meta Ads Daily Data'!I9 | C26: =AVERAGE('Meta Ads Daily Data'!I2:I8) | D26: =IFERROR((B26-C26)/C26,0)
A27: Cost per Purchase | B27: ='Meta Ads Daily Data'!J9 | C27: =AVERAGE('Meta Ads Daily Data'!J2:J8) | D27: =IFERROR((B27-C27)/C27,0)
A28: ROAS | B28: ='Meta Ads Daily Data'!K9 | C28: =AVERAGE('Meta Ads Daily Data'!K2:K8) | D28: =IFERROR((B28-C28)/C28,0)
A30: 4. KEY WINS
A31: ✔ Orders up 28.9% and Gross Sales up 21.6% vs the 7-day average — strongest sales day of the week.
A32: ✔ Meta Ads ROAS at 4.29x, up 22% vs the 7-day average (3.51x); Purchases up 31% (70 vs ~53/day avg).
A33: ✔ "Black DHURANDHAR" campaign ROAS nearly doubled (5.27x vs 2.68x avg) — creative/audience is resonating.
A34: ✔ "Dhirai Scale -ASC" cost per purchase improved 36% (₹527.91 vs ₹823.47 avg) while purchases rose 40%.
A35: ✔ Zero refunds, cancellations, or failed payments recorded yesterday.
A37: 5. KEY ISSUES
A38: ⚠ "New Campaign- for recovery" underperformed its own trend: ROAS down to 3.41x (from 3.73x) and cost per
A39: ⚠ purchase up 20% (₹825.86 vs ₹689.02 avg) — the weakest of the 4 active campaigns yesterday.
A40: ⚠ Shopify session & conversion-rate data has not populated for yesterday (likely reporting lag) — cannot
A41: ⚠ confirm on-site conversion rate for the day; monitor and re-check today.
A42: ⚠ 2 SKUs ("Utsav" Mal Cotton Anarkali Suit Set, "Zariya" Stone Hoops) show 0 units of inventory.
... A51: 5. Archive or delete long-paused campaigns (61 campaigns, $0 spend) to simplify account management.

Sheet Shopify Daily Data
A1: Date | B1: Orders | C1: Gross Sales | D1: Discounts | E1: Returns | F1: Net Sales | G1: Shipping Charges | H1: Taxes | I1: Total Sales | J1: Avg Order Value
A2: 2026-06-24 | B2: 52 | C2: 131811.25 | D2: -1756.37 | E2: 0 | F2: 130054.88 | G2: 0 | H2: 533.75 | I2: 130588.63 | J2: =IFERROR(I2/B2,0)
A3: 2026-06-25 | B3: 49 | C3: 136043 | D3: -5922.29 | E3: 0 | F3: 130120.71 | G3: 0 | H3: 0 | I3: 130120.71 | J3: =IFERROR(I3/B3,0)
A4: 2026-06-26 | B4: 68 | C4: 165729 | D4: -649.75 | E4: 0 | F4: 165079.25 | G4: 0 | H4: 0 | I4: 165079.25 | J4: =IFERROR(I4/B4,0)
A5: 2026-06-27 | B5: 62 | C5: 163386 | D5: -472.3 | E5: -27893 | F5: 135020.7 | G5: 0 | H5: 0 | I5: 135020.7 | J5: =IFERROR(I5/B5,0)
A6: 2026-06-28 | B6: 56 | C6: 143639 | D6: -464.75 | E6: 0 | F6: 143174.25 | G6: 0 | H6: 0 | I6: 143174.25 | J6: =IFERROR(I6/B6,0)
A7: 2026-06-29 | B7: 47 | C7: 120251 | D7: -389.85 | E7: -6899 | F7: 112962.15 | G7: 0 | H7: 0 | I7: 112962.15 | J7: =IFERROR(I7/B7,0)
A8: 2026-06-30 | B8: 57 | C8: 170229 | D8: -2852.37 | E8: 0 | F8: 167376.63 | G8: 0 | H8: 0 | I8: 167376.63 | J8: =IFERROR(I8/B8,0)
A9: 2026-07-01 | B9: 72 | C9: 179124 | D9: -2118.82 | E9: 0 | F9: 177005.18 | G9: 0 | H9: 0 | I9: 177005.18 | J9: =IFERROR(I9/B9,0)

Sheet Meta Ads Daily Data
A1: Date | B1: Amount Spent | C1: Impressions | D1: Reach | E1: Clicks | F1: CTR | G1: CPC | H1: CPM | I1: Purchases | J1: Cost per Purchase | K1: ROAS
A2: 2026-06-24 | B2: 39597.99 | C2: 261473 | D2: 200752 | E2: 5783 | F2: 0.0221 | G2: 6.85 | H2: 151.44 | I2: 51 | J2: =IFERROR(B2/I2,0) | K2: 3.25
A3: 2026-06-25 | B3: 38946.55 | C3: 162777 | D3: 124083 | E3: 4357 | F3: 0.0268 | G3: 8.94 | H3: 239.26 | I3: 47 | J3: =IFERROR(B3/I3,0) | K3: 3.12
A4: 2026-06-26 | B4: 42277.97 | C4: 243521 | D4: 195484 | E4: 5114 | F4: 0.021 | G4: 8.27 | H4: 173.61 | I4: 60 | J4: =IFERROR(B4/I4,0) | K4: 3.45
A5: 2026-06-27 | B5: 32409.25 | C5: 192229 | D5: 148787 | E5: 4153 | F5: 0.0216 | G5: 7.8 | H5: 168.6 | I5: 56 | J5: =IFERROR(B5/I5,0) | K5: 4.42
A6: 2026-06-28 | B6: 43450.69 | C6: 327124 | D6: 255502 | E6: 5714 | F6: 0.0175 | G6: 7.6 | H6: 132.83 | I6: 55 | J6: =IFERROR(B6/I6,0) | K6: 3.22
A7: 2026-06-29 | B7: 39138.71 | C7: 300516 | D7: 252389 | E7: 4951 | F7: 0.0165 | G7: 7.91 | H7: 130.24 | I7: 48 | J7: =IFERROR(B7/I7,0) | K7: 3.13
A8: 2026-06-30 | B8: 40645.6 | C8: 250234 | D8: 201632 | E8: 4738 | F8: 0.0189 | G8: 8.58 | H8: 162.43 | I8: 57 | J8: =IFERROR(B8/I8,0) | K8: 4.13
A9: 2026-07-01 | B9: 40095.88 | C9: 294656 | D9: 247001 | E9: 5338 | F9: 0.0181 | G9: 7.51 | H9: 136.08 | I9: 70 | J9: =IFERROR(B9/I9,0) | K9: 4.29

Sheet Product Performance
A1: Product Performance — Yesterday (2026-07-01)
A3: Product | B3: Gross Sales | C3: Net Sales | D3: Units/Orders | E3: % of Total Gross Sales
A4: Ira Rayon Co-ord Set for Women | Relaxed Fit Shirt Top with Draped Pants | B4: 47481 | C4: 47231.1 | D4: 17 | E4: =B4/179124.0
A5: "The Essential" - White Cotton Shirt & Pant Co-ord Set | B5: 36482 | C5: 36382.05 | D5: 18 | E5: =B5/179124.0
A6: Embroidered Rayon Kurti with Farshi Salwar Set — Elegant Ethnic Co-Ord for Women | B6: 13995 | C6: 13110.51 | D6: 5 | E6: =B6/179124.0
A7: Eclipse Grace Premium Crepe Salwar Suit set | DHIRAI | B7: 11996 | C7: 11996 | D7: 4 | E7: =B7/179124.0
A8: The Dhurandhar Black Short Kurta Set | A Dhirai Essential | B8: 8496 | C8: 8496 | D8: 4 | E8: =B8/179124.0
A9: Elegant Pakistani-Style Mauve Kurta Set | B9: 8396 | C9: 8396 | D9: 4 | E9: =B9/179124.0
A10: Zehra Co-ord set| DHIRAI | B10: 7597 | C10: 7597 | D10: 3 | E10: =B10/179124.0
A11: "Inayat" — Power Pastel Cotton Shirt & Trouser Co-ord Set | B11: 6097 | C11: 6097 | D11: 3 | E11: =B11/179124.0
A12: "Adira" - Premium Breathable Soft Fabric Salwar Set | B12: 5998 | C12: 5998 | D12: 2 | E12: =B12/179124.0
A13: Embroidered Rayon Kurti with Farshi Salwar Set — Elegant Co-Ord for Women | B13: 5598 | C13: 4713.52 | D13: 2 | E13: =B13/179124.0
A14: Kaali Noor Black Cotton Farshi Salwar Set for Women | Elegant Kurta Set | Dhirai | B14: 4398 | C14: 4398 | D14: 1 | E14: =B14/179124.0
A15: "Riva" — Premium Flowy Rayon Co-ord Set | B15: 3998 | C15: 3998 | D15: 2 | E15: =B15/179124.0
... A18: "Gulab" – Mauve Pink Premium Rayon Co-ord Set with Cream Lace Details | B18: 2499 | C18: 2499 | D18: 1 | E18: =B18/179124.0

Sheet Campaign Performance
A1: Campaign Performance — Yesterday (2026-07-01) vs Previous 7-Day Average (2026-06-24 to 2026-06-30)
A3: Campaign | B3: Status | C3: Spend (Yesterday) | D3: Spend (7-day avg) | E3: Purchases (Yesterday) | F3: Purchases (7-day avg) | G3: ROAS (Yesterday) | H3: ROAS (7-day avg) | I3: Cost/Purchase (Yesterday) | J3: Cost/Purchase (7-day avg) | K3: CTR (Yesterday) | L3: CPC (Yesterday)
A4: New Campaign- for recovery | B4: ACTIVE | C4: 12387.89 | D4: 11811.7 | E4: 15 | F4: 17.142857 | G4: 3.41 | H4: 3.73 | I4: 825.86 | J4: 689.01583 | K4: 0.0102 | L4: 7.03
A5: Retargeting- new | B5: ACTIVE | C5: 6996.3 | D5: 6165.8343 | E5: 14 | F5: 10.571429 | G5: 4.94 | H5: 4.68 | I5: 499.74 | J5: 583.25459 | K5: 0.0364 | L5: 9.61
A6: Dhirai Scale -ASC | B6: ACTIVE | C6: 12141.98 | D6: 13528.39 | E6: 23 | F6: 16.428571 | G6: 4.12 | H6: 3.26 | I6: 527.91 | J6: 823.46722 | K6: 0.0246 | L6: 7.26
A7: Black DHURANDHAR | B7: ACTIVE | C7: 8569.71 | D7: 7989.3271 | E7: 18 | F7: 9.2857143 | G7: 5.27 | H7: 2.68 | I7: 476.1 | J7: 860.38908 | K7: 0.0344 | L7: 7.28

Sheet Recommendations & Notes
A1: Recommendations & Notes
A3: RECOMMENDED ACTIONS (business-focused)
A4: • Scale winning campaigns: increase daily budget on "Black DHURANDHAR" (ROAS 5.27x) and "Dhirai Scale -ASC"
A5: (ROAS 4.12x, cost/purchase down 36%) — both are outperforming their own 7-day trend.
A6: • Investigate/refresh "New Campaign- for recovery": ROAS slipped to 3.41x (from 3.73x avg) and cost per
A7: purchase rose ~20%. Test new creative or narrow targeting before adding more budget.
A8: • Fix inventory gaps: restock or temporarily unpublish "Utsav" Mal Cotton Anarkali Suit Set and "Zariya"
A9: Stone Hoops — both show 0 units available.
A10: • Investigate tracking: Shopify session/conversion-rate data was not available for yesterday at run time.
A11: Confirm Shopify Analytics is processing normally; re-check this figure later today.
A12: • Clean up ad account: 61 of 65 campaigns are PAUSED with $0 spend. Archive stale tests/duplicates to keep
A13: the account easy to audit.
... A33: same tab structure, formatting, and formulas instead, and emailed as an attachment where possible.
